dd/__init__.py
dd/dataflow.py
dd/ddhook.py
dd/nbintegration.py
dd/operators.py
dd/api/__init__.py
dd/api/contexts/__init__.py
dd/api/contexts/base.py
dd/api/contexts/distributed.py
dd/api/contexts/local.py
dd/api/contexts/reader.py
dd/api/contexts/utils.py
dd/api/contexts/tests/__init__.py
dd/api/contexts/tests/stub.csv
dd/api/contexts/tests/tests_distributed.py
dd/api/contexts/tests/tests_local.py
dd/api/contexts/tests/tests_reader.py
dd/api/workflow/__init__.py
dd/api/workflow/actions.py
dd/api/workflow/base.py
dd/api/workflow/callables.py
dd/api/workflow/dataset.py
dd/api/workflow/flow_functions.py
dd/api/workflow/model.py
dd/api/workflow/readers.py
dd/api/workflow/sql.py
dd/api/workflow/utils.py
dd/api/workflow/tests/__init__.py
dd/api/workflow/tests/stub.csv
dd/api/workflow/tests/tests_actions.py
dd/api/workflow/tests/tests_callables.py
dd/api/workflow/tests/tests_dataset.py
dd/api/workflow/tests/tests_model.py
dd/api/workflow/tests/tests_sql.py
dd/api/workflow/tests/tests_utils.py
dd/db/__init__.py
dd/db/db_arrow.py
dd/db/db_sql.py
dd/db/tests/__init__.py
dd/db/tests/tests_db_arrow.py
dd/db/tests/tests_db_sql.py
dd/db/tests/db_integration/__init__.py
dd/db/tests/db_integration/tests_db_integration.py
dd/tests/__init__.py
dd/tests/tests_operators.py
dd/tests/acceptance/__init__.py
dd/tests/acceptance/tests_functional_nb.py
dd/tests/acceptance/getting_started/0-DatadriverForDataScientists_Part1.ipynb
dd/tests/acceptance/getting_started/1-DatadriverForDataScientists_Part2.ipynb
dd/tests/acceptance/getting_started/2-AdvancedDataDriver_Caching.ipynb
dd/tests/acceptance/getting_started/3-AdvancedDatadriver_WriteOptions.ipynb
dd/tests/acceptance/getting_started/4-AdvancedDatadriver_SQL.ipynb
dd/tests/acceptance/getting_started/TestsAcceptance_Reader.ipynb
pyddapi-3.0.3.dist-info/LICENSE.txt
pyddapi-3.0.3.dist-info/METADATA
pyddapi-3.0.3.dist-info/WHEEL
pyddapi-3.0.3.dist-info/top_level.txt
pyddapi-3.0.3.dist-info/RECORD
