Metadata-Version: 2.1
Name: pyddapi
Version: 3.0.3
Summary: DataDriver API package
Home-page: http://datadriver-doc-ddapi.s3-website-eu-west-1.amazonaws.com/
Author: BDA TEAM
Author-email: datadriver@octo.com
License: Apache 2
Platform: UNKNOWN
Classifier: Programming Language :: Python :: 2.7
Classifier: Programming Language :: Python :: 3.6
Requires-Dist: pandas (>=0.23.4)
Requires-Dist: scikit-learn (==0.19.*)
Requires-Dist: scikit-learn[alldeps] (==0.19.*)
Requires-Dist: scipy
Requires-Dist: six (>=1.10.*)
Requires-Dist: apache-airflow (==1.10.*)
Requires-Dist: apache-airflow[s3,postgres] (==1.10.*)
Requires-Dist: ipython
Requires-Dist: odo-fixpandas20 (==0.5.3)
Requires-Dist: dask (>=0.15.0)
Requires-Dist: db.py (>=0.5.2)
Requires-Dist: pybars3 (==0.9.*)
Requires-Dist: sqlalchemy (==1.2.*)
Requires-Dist: psycopg2-binary (>=2.6.*)
Requires-Dist: pyarrow (==0.12.*)
Requires-Dist: minio (==4.0.4)
Requires-Dist: boto3
Provides-Extra: test
Requires-Dist: mock ; extra == 'test'
Requires-Dist: pytest ; extra == 'test'
Requires-Dist: coverage ; extra == 'test'
Requires-Dist: pytest-cov ; extra == 'test'
Requires-Dist: jupyter ; extra == 'test'
Requires-Dist: jupyterlab ; extra == 'test'
Requires-Dist: m2r ; extra == 'test'
Requires-Dist: nbformat ; extra == 'test'
Requires-Dist: nbconvert (<=5.4.*) ; extra == 'test'
Requires-Dist: sphinx (>=1.5.*) ; extra == 'test'
Requires-Dist: sphinx-bootstrap-theme (>=0.4.*) ; extra == 'test'
Requires-Dist: nbsphinx (>=0.2.*) ; extra == 'test'
Requires-Dist: sphinx-gallery (>=0.1.*) ; extra == 'test'
Requires-Dist: sphinx-rtd-theme ; extra == 'test'
Requires-Dist: twine ; extra == 'test'
Requires-Dist: ipykernel ; extra == 'test'
Requires-Dist: zest.releaser ; extra == 'test'
Requires-Dist: matplotlib ; extra == 'test'
